[
  {
    "content": "彼は遅刻した。（　　）資料も忘れた。",
    "options": {
      "A": "そればかりか",
      "B": "それとも",
      "C": "それにしても",
      "D": "それで"
    },
    "correct_answer": "A",
    "explanation": "[本题考点]: 测试「そればかりか」的递进用法，强调后项比前项更严重或更极端。[语境分析]: 前项「遅刻した」已经是不好的行为，后项「資料も忘れた」是更严重的过失，需要表达递进关系的接续词。[选项解析]: A「そればかりか」正确，符合递进逻辑；B「それとも」用于选择疑问句，不符；C「それにしても」表示转折或让步，不符；D「それで」表示因果关系，不符。",
    "memorization_tip": "「そればかりか」=「不仅…而且更糟」，记住后项一定比前项更极端。",
    "hash": "ac8303b3186c9c1738c88236d292cd4a44b2e7dc04f81d9bc768dfb656fb018c",
    "knowledge_point": "そればかりか"
  },
  {
    "content": "彼女は日本語が上手だ。（　　）フランス語も話せる。",
    "options": {
      "A": "そればかりか",
      "B": "そのうえ",
      "C": "それどころか",
      "D": "それに"
    },
    "correct_answer": "B",
    "explanation": "[本题考点]: 测试「そればかりか」与近义表达「そのうえ」的区别。[语境分析]: 前项「日本語が上手」是优点，后项「フランス語も話せる」是追加的优点，无极端对比，需用中性递进词。[选项解析]: B「そのうえ」正确，表示单纯追加；A「そればかりか」虽可递进但隐含「更极端」语义，此处不适用；C「それどころか」用于否定前项，不符；D「それに」语气较弱，多用于口语。",
    "memorization_tip": "中性追加用「そのうえ」，极端递进才用「そればかりか」。",
    "hash": "810d6c253bb13aaccc8b097ffc71f6c22bb4490ec1356a66693e3e2ab851b521",
    "knowledge_point": "そればかりか",
    "is_favorite": true
  },
  {
    "content": "台風で電車が止まった。（　　）道路も通行止めになった。",
    "options": {
      "A": "そればかりか",
      "B": "それなら",
      "C": "それから",
      "D": "それほど"
    },
    "correct_answer": "A",
    "explanation": "[本题考点]: 测试「そればかりか」在负面情境中的递进用法。[语境分析]: 前项「電車が止まった」是灾害影响，后项「道路も通行止め」是更严重的后果，需强递进。[选项解析]: A「そればかりか」正确，强调事态恶化；B「それなら」表示假设，不符；C「それから」仅表时间顺序，无递进；D「それほど」用于程度否定，结构错误。",
    "memorization_tip": "灾难升级场景优先考虑「そればかりか」。",
    "hash": "1e8886652ed825d6676c6a5150c4c4c33e7f15d56d667d2a0d5c7d48aae59d6c",
    "knowledge_point": "そればかりか"
  },
  {
    "content": "このレストランは味が良い。（　　）値段も手頃だ。",
    "options": {
      "A": "そればかりか",
      "B": "むしろ",
      "C": "かえって",
      "D": "それに"
    },
    "correct_answer": "D",
    "explanation": "[本题考点]: 测试「そればかりか」在正面语境中的误用。[语境分析]: 前后项均为优点但无极端对比，需用中性追加词。[选项解析]: D「それに」正确，表追加优点；A「そればかりか」过度强调递进，不自然；B「むしろ」用于对比优选，不符；C「かえって」表逆向结果，不符。",
    "memorization_tip": "并列优点用「それに」，极端递进才用「そればかりか」。",
    "hash": "8a1d2e26880e0fb346508989f69457e91fd61c4126c9a3b2a49a6bc8f260cedf",
    "knowledge_point": "そればかりか"
  },
  {
    "content": "彼は約束を破った。（　　）謝りもしなかった。",
    "options": {
      "A": "そればかりか",
      "B": "それなのに",
      "C": "それでも",
      "D": "それこそ"
    },
    "correct_answer": "A",
    "explanation": "[本题考点]: 测试「そればかりか」在道德批判场景中的使用。[语境分析]: 前项「約束を破った」已是不当行为，后项「謝りもしない」是更恶劣的态度，需强递进。[选项解析]: A「そればかりか」正确，凸显行为升级；B「それなのに」表意外转折，无递进；C「それでも」表让步，不符；D「それこそ」用于强调特定事例，结构错误。",
    "memorization_tip": "道德批判+行为恶化=「そればかりか」铁则。",
    "hash": "980c1a64d38e9112db99fec1a760cc1f0bcaf4c112f54d39a42e38a20a603971",
    "knowledge_point": "そればかりか"
  },
  {
    "content": "彼は仕事を辞めた。（　　）家族にも相談していなかった。",
    "options": {
      "A": "そればかりか",
      "B": "それとも",
      "C": "それにしても",
      "D": "それで"
    },
    "correct_answer": "A",
    "explanation": "[本题考点]: 测试「そればかりか」的递进用法，表示前项情况已很严重，后项更进一步。\n[语境分析]: 前句「仕事を辞めた」已是重大决定，后句「家族にも相談していなかった」程度更甚，符合「そればかりか」的递进逻辑。\n[选项解析]: A正确，表示「不仅辞职，甚至没和家人商量」的递进关系；B「それとも」用于二选一（书面语），C「それにしても」表转折（即便如此），D「それで」表因果关系，均不符合语境。",
    "memorization_tip": "联想记忆：「ばかり」表示程度超出预期，后项比前项更极端，类似中文「岂止…简直…」",
    "hash": "bdc56a2f67026aa10242bc7b6fd65086af4d6840ccc26891d4ab45d7874059f2",
    "knowledge_point": "そればかりか"
  },
  {
    "content": "試験に失敗した。（　　）体調まで崩してしまった。",
    "options": {
      "A": "それに",
      "B": "そればかりか",
      "C": "それほど",
      "D": "それなら"
    },
    "correct_answer": "B",
    "explanation": "[本题考点]: 考察「そればかりか」在负面情况叠加时的递进强调。\n[语境分析]: 前项「試験失敗」已是挫折，后项「体調不良」是更严重的追加状况，需用表极端递进的接续词。\n[选项解析]: B正确，强调「考试失败不说，还搞垮了身体」的恶化关系；A「それに」仅表并列添加，C「それほど」表程度（不接句子），D「それなら」表假设（既然那样），均无法体现递进恶化。",
    "memorization_tip": "对比记忆：「それに」单纯添加信息，「そればかりか」带有「雪上加霜」的语感",
    "hash": "5116a2ffe2c9a8a82dc4b16e53c09396288832265e7202c6d29cbe863167d3ee",
    "knowledge_point": "そればかりか"
  },
  {
    "content": "新製品は機能が優れている。（　　）デザインも革新的だ。",
    "options": {
      "A": "そればかりか",
      "B": "というより",
      "C": "かえって",
      "D": "むしろ"
    },
    "correct_answer": "A",
    "explanation": "[本题考点]: 测试「そればかりか」在积极语境中的递进用法。\n[语境分析]: 前项「機能優秀」是优点，后项「デザイン革新」是追加的亮点，需用表递进强调的接续词。\n[选项解析]: A正确，表示「功能优秀不说，设计还很创新」的递进褒义；B「というより」表修正说法（与其说…不如说…），C「かえって」表逆向结果，D「むしろ」表对比选择，均不符合褒义递进逻辑。",
    "memorization_tip": "注意：递进关系不仅用于负面，积极语境中也可表示「锦上添花」",
    "hash": "f09fc1e0b31ae00ebd2a9208d4a45e679c75715f6027f82e6a45f881136ac8e0",
    "knowledge_point": "そればかりか"
  },
  {
    "content": "彼女は英語が堪能だ。（　　）フランス語も話せる。",
    "options": {
      "A": "それどころか",
      "B": "そればかりか",
      "C": "それなのに",
      "D": "それだけに"
    },
    "correct_answer": "B",
    "explanation": "[本题考点]: 区分「そればかりか」与近义语法「それどころか」的微妙差异。\n[语境分析]: 前项「英語堪能」是高水平能力，后项「フランス語も話せる」是追加能力，属于同类递进。\n[选项解析]: B正确，表示「英语好不说，还会法语」的同类能力叠加；A「それどころか」用于否定前项（别说英语了…），C「それなのに」表转折，D「それだけに」表因果关系，均不适用。",
    "memorization_tip": "关键区别：「それどころか」否定前项，「そればかりか」承认前项并追加更强后项",
    "hash": "ab0da77c4bd995ee093754ab43d86ad848298ff6ffb376c7c03c3de48aa519b3",
    "knowledge_point": "そればかりか"
  },
  {
    "content": "このレストランは味がまずい。（　　）値段も高い。",
    "options": {
      "A": "それに",
      "B": "そればかりか",
      "C": "それこそ",
      "D": "それまで"
    },
    "correct_answer": "B",
    "explanation": "[本题考点]: 验证「そればかりか」在双重负面评价中的核心功能。\n[语境分析]: 前项「味まずい」是缺点，后项「値段高い」是更令人不满的追加缺点，需用表极端递进的接续词。\n[选项解析]: B正确，强调「难吃不说，还贵」的递进不满；A「それに」语气较弱，C「それこそ」表极端举例（那才真是…），D「それまで」表截止期限（到那时为止），均无法表达强烈递进批判。",
    "memorization_tip": "情感强化：后项比前项更让人难以忍受时，必用「そればかりか」",
    "hash": "2d34c9c7a2e99828554652cf68754147d0f657d3d6107dd838957aa5896a52ed",
    "knowledge_point": "そればかりか"
  }
]